tcs34725.py
tcs34725-1.0.1.dist-info/METADATA
tcs34725-1.0.1.dist-info/WHEEL
tcs34725-1.0.1.dist-info/top_level.txt
tcs34725-1.0.1.dist-info/RECORD
