Metadata-Version: 2.1
Name: tcs34725
Version: 1.0.1
Summary: Driver for MicroPython for the tcs34725 RGB sensor.
Home-page: https://github.com/adafruit/micropython-adafruit-tcs34725
Author: Radomir Dopieralski
Author-email: micropython@sheep.art.pl
Classifier: Programming Language :: Python :: 3
Classifier: License :: OSI Approved :: MIT License
Classifier: Operating System :: OS Independent
Requires-Python: >=3.6
